enhanced_pipeline/__init__.py
enhanced_pipeline/enhanced_pipeline.py
enhanced_pipeline-0.1.0.dist-info/LICENSE
enhanced_pipeline-0.1.0.dist-info/METADATA
enhanced_pipeline-0.1.0.dist-info/WHEEL
enhanced_pipeline-0.1.0.dist-info/top_level.txt
enhanced_pipeline-0.1.0.dist-info/RECORD
