Metadata-Version: 2.1
Name: enhanced_pipeline
Version: 0.1.0
Summary: A enhanced multi-worker parallel processing pipeline implementation in Python 
Author-email: Ameer fayiz <amrjets@gmail.com>
Project-URL: Homepage, https://github.com/ameerfayiz/enhanced_pipeline
Project-URL: Bug Tracker, https://github.com/ameerfayiz/enhanced_pipeline/issues
Classifier: Programming Language :: Python :: 3
Classifier: License :: OSI Approved :: MIT License
Classifier: Operating System :: OS Independent
Classifier: Development Status :: 4 - Beta
Classifier: Intended Audience :: Developers
Classifier: Topic :: Software Development :: Libraries :: Python Modules
Requires-Python: >=3.8
License-File: LICENSE
